discord_sender/__init__.py
discord_sender/__main__.py
discord_sender/channel.py
discord_sender/discord.py
discord_sender/discord_exceptions.py
discord_sender/info.py
discord_sender/other.py
discord_sender/tools.py
discord_sender-2.0.4.dist-info/LICENSE
discord_sender-2.0.4.dist-info/METADATA
discord_sender-2.0.4.dist-info/WHEEL
discord_sender-2.0.4.dist-info/RECORD
