Metadata-Version: 2.1
Name: discord-sender
Version: 2.0.4
Summary: A discord module that lets you send messages as a user
Home-page: https://github.com/Jacoblightning/discord-sender
License: Unlicense
Keywords: bot,discord,discordbot,user-bot
Author: Jacob
Author-email: 112590190+Jacoblightning@users.noreply.github.com
Requires-Python: >=3.10
Classifier: License :: OSI Approved
Classifier: Programming Language :: Python :: 3
Classifier: Programming Language :: Python :: 3.10
Classifier: Programming Language :: Python :: 3.11
Classifier: Programming Language :: Python :: 3.12
Requires-Dist: requests
Project-URL: Documentation, https://github.com/Jacoblightning/discord-sender/blob/main/README.md
Project-URL: Repository, https://github.com/Jacoblightning/discord-sender
